{
  "main": {
    "id": "dec83ebe87a647f5",
    "type": "split",
    "children": [
      {
        "id": "953b72c067113e04",
        "type": "tabs",
        "children": [
          {
            "id": "5b8b92e22383abd9",
            "type": "leaf",
            "state": {
              "type": "markdown",
              "state": {
                "file": "Notes/2023-03-03.md",
                "mode": "source",
                "source": false
              }
            }
          },
          {
            "id": "240a52e2f6b33912",
            "type": "leaf",
            "state": {
              "type": "markdown",
              "state": {
                "file": "Notes/2023-03-03.md",
                "mode": "source",
                "source": false
              }
            }
          },
          {
            "id": "17f38e3dd6baa316",
            "type": "leaf",
            "state": {
              "type": "markdown",
              "state": {
                "file": "MSP/Discussions/Access Control Policies Definitions.md",
                "mode": "source",
                "source": false
              }
            }
          },
          {
            "id": "b08a866cb9842300",
            "type": "leaf",
            "state": {
              "type": "markdown",
              "state": {
                "file": "MSP/Discussions/ASPCA - CISO GLOBAL Datto Talk 3-1-2023.md",
                "mode": "source",
                "source": false
              }
            }
          }
        ],
        "currentTab": 1
      }
    ],
    "direction": "vertical"
  },
  "left": {
    "id": "9250f43d06e00a3c",
    "type": "split",
    "children": [
      {
        "id": "0ed4cafa81a0c580",
        "type": "tabs",
        "children": [
          {
            "id": "8cf619db944c2c1e",
            "type": "leaf",
            "state": {
              "type": "file-explorer",
              "state": {
                "sortOrder": "alphabeticalReverse"
              }
            }
          },
          {
            "id": "f04ef8469680a73d",
            "type": "leaf",
            "state": {
              "type": "search",
              "state": {
                "query": "tag:#MSP",
                "matchingCase": false,
                "explainSearch": false,
                "collapseAll": false,
                "extraContext": false,
                "sortOrder": "alphabetical"
              }
            }
          },
          {
            "id": "c743ff1ad11e12f3",
            "type": "leaf",
            "state": {
              "type": "starred",
              "state": {}
            }
          },
          {
            "id": "2a527fdae39bff1d",
            "type": "leaf",
            "state": {
              "type": "tag",
              "state": {
                "sortOrder": "frequency",
                "useHierarchy": true
              }
            }
          }
        ]
      }
    ],
    "direction": "horizontal",
    "width": 305.5
  },
  "right": {
    "id": "f4b67e458784d2f3",
    "type": "split",
    "children": [
      {
        "id": "c5286467d96118ec",
        "type": "tabs",
        "children": [
          {
            "id": "e6cd65d3c946556a",
            "type": "leaf",
            "state": {
              "type": "backlink",
              "state": {
                "file": "Notes/2023-03-03.md",
                "collapseAll": false,
                "extraContext": false,
                "sortOrder": "alphabetical",
                "showSearch": false,
                "searchQuery": "",
                "backlinkCollapsed": false,
                "unlinkedCollapsed": true
              }
            }
          },
          {
            "id": "f6cee2b8b7e035b1",
            "type": "leaf",
            "state": {
              "type": "outgoing-link",
              "state": {
                "file": "Notes/2023-03-03.md",
                "linksCollapsed": false,
                "unlinkedCollapsed": true
              }
            }
          },
          {
            "id": "17c60b2f81ad9654",
            "type": "leaf",
            "state": {
              "type": "outline",
              "state": {
                "file": "Notes/2023-03-03.md"
              }
            }
          },
          {
            "id": "b48c23b487888207",
            "type": "leaf",
            "state": {
              "type": "advanced-tables-toolbar",
              "state": {}
            }
          },
          {
            "id": "21fabe581ec7e08e",
            "type": "leaf",
            "state": {
              "type": "side-panel-control-view",
              "state": {}
            }
          }
        ],
        "currentTab": 4
      }
    ],
    "direction": "horizontal",
    "width": 300,
    "collapsed": true
  },
  "left-ribbon": {
    "hiddenItems": {
      "switcher:Open quick switcher": false,
      "graph:Open graph view": true,
      "canvas:Create new canvas": true,
      "daily-notes:Open today's daily note": false,
      "templates:Insert template": false,
      "command-palette:Open command palette": true,
      "table-editor-obsidian:Advanced Tables Toolbar": false,
      "homepage:Open homepage": false,
      "obsidian-markdown-formatting-assistant-plugin:Open Markdown Formatting Assistant": false,
      "obsidian-excalidraw-plugin:Create new drawing": true,
      "mermaid-tools:Open Mermaid Toolbar": false
    }
  },
  "active": "240a52e2f6b33912",
  "lastOpenFiles": [
    "MSP/Network Management and Monitoring.md",
    "Home.md",
    "Notes/Intune Infra Readiness.md",
    "Notes/2023-03-03.md",
    "MSP/Discussions/ASPCA - CISO GLOBAL Datto Talk 3-1-2023.md",
    "MSP/Discussions/Access Control Policies Definitions.md",
    "Azure/Membership Profile Permission Mapping.md",
    "Azure/Azure Documentation/Azure Docs - Setting up Storage Account with SFTP.md",
    "MSP/Discussions/Network Talk - 3-1-2023.md",
    "Notes/MSP.md",
    "Notes/BackBurner.md",
    "Notes/2023-03-01.md",
    "Azure/Azure Documentation Home.md",
    "Azure/Azure Documentation/Azure Docs - Networking - Azure Firewall Setup for Traffic Forced.md",
    "Azure/Azure Documentation/Azure Docs - Networking - Azure Firewall Setup for Traffic Forced",
    "Azure/Azure Documentation/Azure Docs - Networking - Setting u",
    "Azure/Azure Documentation/Azure Docs -",
    "README.md",
    "Obsidian-Ilya",
    "Templates/TEMPLATE-Daily Notes.md",
    "Home Canvas.canvas",
    "Azure/Azure Documentation Checklist.md",
    "Azure/Azure Documentation",
    "IMAGES/Pasted image 20230302173058.png",
    "Notes/Retention Backups tape.md",
    "Notes/DirSync - Azure AD Connect.md",
    "Untitled Kanban.md",
    "Excalidraw/Drawing 2023-03-02 16.38.23.excalidraw.md",
    "Cheatsheets/MARKDOWN CHEATSHEET.md",
    "Synapse Permissions De-Mystified.md",
    "ScratchPad/Flow Chart Example.md",
    "Excalidraw",
    "IMAGES/Pasted image 20230302153425.png",
    "IMAGES/Pasted image 20230302153359.png",
    "ScratchPad/Legal Compliance.md",
    "ScratchPad/Scratch.md",
    "IMAGES/Pasted image 20230302114952.png",
    "Unorganized",
    "MSP/Discussions",
    "MSP",
    "IMAGES/Document Retention and Destruction Policy 1-5-22 - FINAL.pdf",
    "IMAGES/Pasted image 20230224135720.png"
  ]
}